README
setup.py
markup_utils/__init__.py
markup_utils/filters.py
markup_utils/manage.py
markup_utils/templatetags/__init__.py
markup_utils/templatetags/markuptags.py
markuputils.egg-info/PKG-INFO
markuputils.egg-info/SOURCES.txt
markuputils.egg-info/dependency_links.txt
markuputils.egg-info/not-zip-safe
markuputils.egg-info/top_level.txt