Metadata-Version: 1.0
Name: markuputils
Version: 0.3dev
Summary: Markup utilities for Django applications.
Home-page: http://github.com/ctrochalakis/django-markuputils
Author: Christos Trochalakis
Author-email: yatiohi@ideopolis.gr
License: UNKNOWN
Platform: UNKNOWN
Classifier: Development Status :: 4 - Beta
Classifier: Environment :: Web Environment
Classifier: Intended Audience :: Developers
Classifier: License :: OSI Approved :: BSD License
Classifier: Operating System :: OS Independent
Classifier: Programming Language :: Python
Classifier: Framework :: Django
Classifier: Topic :: Utilities
